pelican_thumbnail
