Metadata-Version: 1.1
Name: pelican-thumbnail
Version: 0.2
Summary: A Pelican plugin to add a thumbnail for the article.
Home-page: https://github.com/wutali/pelican_thumbnail
Author: Takahiro Fujiwara
Author-email: email@wuta.li
License: UNKNOWN
Download-URL: https://github.com/wutali/pelican_thumbnail/tarball/master
Platform: UNKNOWN
